[
  {
    "_id": "faph001",
    "activityId": "fa002",
    "url": "https://images.unsplash.com/photo-1461896836934- voices?w=800",
    "thumbnailUrl": "https://images.unsplash.com/photo-1461896836934- voices?w=200",
    "description": "运动会开场，大家准备开始运动啦！",
    "uploadedBy": "u001",
    "uploaderNickname": "爸爸",
    "uploadedAt": 1746262800000,
    "createdAt": 1746262800000,
    "updatedAt": 1746262800000
  },
  {
    "_id": "faph002",
    "activityId": "fa002",
    "url": "https://images.unsplash.com/photo-1571019613454-1cb2f99b2d8b?w=800",
    "thumbnailUrl": "https://images.unsplash.com/photo-1571019613454-1cb2f99b2d8b?w=200",
    "description": "接力赛，小明和小红配合默契",
    "uploadedBy": "u002",
    "uploaderNickname": "妈妈",
    "uploadedAt": 1746264600000,
    "createdAt": 1746264600000,
    "updatedAt": 1746264600000
  },
  {
    "_id": "faph003",
    "activityId": "fa002",
    "url": "https://images.unsplash.com/photo-1534438327276-14e5300c3a48?w=800",
    "thumbnailUrl": "https://images.unsplash.com/photo-1534438327276-14e5300c3a48?w=200",
    "description": "拔河比赛，全家人一起加油",
    "uploadedBy": "u001",
    "uploaderNickname": "爸爸",
    "uploadedAt": 1746266400000,
    "createdAt": 1746266400000,
    "updatedAt": 1746266400000
  },
  {
    "_id": "faph004",
    "activityId": "fa002",
    "url": "https://images.unsplash.com/photo-1569517282132-25d22f4573e6?w=800",
    "thumbnailUrl": "https://images.unsplash.com/photo-1569517282132-25d22f4573e6?w=200",
    "description": "颁奖时刻，小明获得最佳表现奖！",
    "uploadedBy": "u002",
    "uploaderNickname": "妈妈",
    "uploadedAt": 1746268200000,
    "createdAt": 1746268200000,
    "updatedAt": 1746268200000
  },
  {
    "_id": "faph005",
    "activityId": "fa003",
    "url": "https://images.unsplash.com/photo-1585647347483-22b66260dfff?w=800",
    "thumbnailUrl": "https://images.unsplash.com/photo-1585647347483-22b66260dfff?w=200",
    "description": "准备了爆米花和可乐",
    "uploadedBy": "u004",
    "uploaderNickname": "小红",
    "uploadedAt": 1745681400000,
    "createdAt": 1745681400000,
    "updatedAt": 1745681400000
  },
  {
    "_id": "faph006",
    "activityId": "fa003",
    "url": "https://images.unsplash.com/photo-1489599849927-2ee91cede3ba?w=800",
    "thumbnailUrl": "https://images.unsplash.com/photo-1489599849927-2ee91cede3ba?w=200",
    "description": "一起看《疯狂动物城》",
    "uploadedBy": "u003",
    "uploaderNickname": "小明",
    "uploadedAt": 1745685000000,
    "createdAt": 1745685000000,
    "updatedAt": 1745685000000
  },
  {
    "_id": "faph007",
    "activityId": "fa003",
    "url": "https://images.unsplash.com/photo-1517604931442-7e0c8ed2963c?w=800",
    "thumbnailUrl": "https://images.unsplash.com/photo-1517604931442-7e0c8ed2963c?w=200",
    "description": "看完电影大家热烈讨论剧情",
    "uploadedBy": "u001",
    "uploaderNickname": "爸爸",
    "uploadedAt": 1745688600000,
    "createdAt": 1745688600000,
    "updatedAt": 1745688600000
  },
  {
    "_id": "faph008",
    "activityId": "fa003",
    "url": "https://images.unsplash.com/photo-1528605248644-14dd04022da1?w=800",
    "thumbnailUrl": "https://images.unsplash.com/photo-1528605248644-14dd04022da1?w=200",
    "description": "美好的家庭电影之夜合影留念",
    "uploadedBy": "u002",
    "uploaderNickname": "妈妈",
    "uploadedAt": 1745690400000,
    "createdAt": 1745690400000,
    "updatedAt": 1745690400000
  }
]
